sp_ccrawl/conf.py
sp_ccrawl/sparkcc.py
sp_ccrawl-0.5.dist-info/DESCRIPTION.rst
sp_ccrawl-0.5.dist-info/METADATA
sp_ccrawl-0.5.dist-info/RECORD
sp_ccrawl-0.5.dist-info/WHEEL
sp_ccrawl-0.5.dist-info/metadata.json
sp_ccrawl-0.5.dist-info/top_level.txt
