Metadata-Version: 2.0
Name: sp-ccrawl
Version: 0.5
Summary: The base for commoncrawl analysis based on sparkcc
Home-page: http://github.com/rtaubes/spcc
Author: Roman Taubes
Author-email: roman.taubes@gmail.com
License: MIT
Keywords: spark commoncrawl
Platform: UNKNOWN
Classifier: Development Status :: 5 - Production/Stable
Classifier: License :: OSI Approved :: MIT License
Classifier: Programming Language :: Python :: 3
Classifier: Topic :: Software Development :: Libraries
Requires-Dist: boto3
Requires-Dist: botocore
Requires-Dist: warcio
